gift_wrapper/__init__.py
gift_wrapper/colors.py
gift_wrapper/core.py
gift_wrapper/gift.py
gift_wrapper/image.py
gift_wrapper/latex.py
gift_wrapper/parsing.py
gift_wrapper/question.py
gift_wrapper/remote.py
gift_wrapper/transformer.py
gift_wrapper-1.8.1.dist-info/licenses/LICENSE
gift_wrapper-1.8.1.dist-info/METADATA
gift_wrapper-1.8.1.dist-info/WHEEL
gift_wrapper-1.8.1.dist-info/entry_points.txt
gift_wrapper-1.8.1.dist-info/top_level.txt
gift_wrapper-1.8.1.dist-info/RECORD
