Metadata-Version: 2.4
Name: gift-wrapper
Version: 1.8.1
Summary: Build GIFT (Moodle compatible) files easily
Home-page: https://github.com/manuvazquez/gift-wrapper
Author: Manuel A. Vázquez
Author-email: manuavazquez@gmail.com
Requires-Python: >=3.10
License-File: LICENSE
Requires-Dist: colorama>=0.4.6
Requires-Dist: paramiko>=3.5.1
Requires-Dist: pyyaml>=6.0.2
Requires-Dist: tqdm>=4.67.1
Dynamic: author
Dynamic: author-email
Dynamic: home-page
Dynamic: license-file
Dynamic: requires-python
